CODE_OF_CONDUCT.md
LICENSE
README.md
momPortsRets.png
momRetsMean2.png
requirements.txt
setup.cfg
setup.py
.github/ISSUE_TEMPLATE/bug_report.md
.github/ISSUE_TEMPLATE/custom.md
.github/ISSUE_TEMPLATE/feature_request.md
QuantFin/HandleError.py
QuantFin/MarketRisk.py
QuantFin/PanelRegs.py
QuantFin/Portfolio.py
QuantFin/Proxy.py
QuantFin/ReqData.py
QuantFin/__init__.py
QuantFin/_deciles.py
QuantFin/_regression.py
QuantFin/tool.py
QuantFin.egg-info/PKG-INFO
QuantFin.egg-info/SOURCES.txt
QuantFin.egg-info/dependency_links.txt
QuantFin.egg-info/requires.txt
QuantFin.egg-info/top_level.txt