Metadata-Version: 2.1
Name: QuantFin
Version: 0.0.9
Summary: Library for Academic Research on Asset Pricing
Home-page: https://github.com/yuz0101/QuantFin
Download-URL: https://github.com/yuz0101/QuantFin/archive/refs/tags/0.0.9.zip
Author: Stephen Zhang
Author-email: stephen_se@outlook.com
License: MIT
Keywords: ACADEMIC,EMPIRICAL,FIANCE,RESEARCH,QUANT,PORTFOLIO
Classifier: Intended Audience :: Developers
Classifier: License :: OSI Approved :: MIT License
Classifier: Programming Language :: Python
Classifier: Programming Language :: Python :: 3
Classifier: Programming Language :: Python :: 3.9
Classifier: Programming Language :: Python :: 3.10
Classifier: Programming Language :: Python :: 3.11
Classifier: Operating System :: OS Independent
License-File: LICENSE
